sphinx_confluencebuilder_bridge/__init__.py
sphinx_confluencebuilder_bridge/py.typed
sphinx_confluencebuilder_bridge-2025.11.16.dist-info/licenses/LICENSE
sphinx_confluencebuilder_bridge-2025.11.16.dist-info/METADATA
sphinx_confluencebuilder_bridge-2025.11.16.dist-info/WHEEL
sphinx_confluencebuilder_bridge-2025.11.16.dist-info/top_level.txt
sphinx_confluencebuilder_bridge-2025.11.16.dist-info/RECORD
