Metadata-Version: 2.4
Name: sphinx-confluencebuilder-bridge
Version: 2025.11.16
Summary: Extension for Sphinx which enables using directives and roles from Atlassian® Confluence® Builder for Sphinx in other Sphinx builders such as HTML.
Author-email: Adam Dangoor <adamdangoor@gmail.com>
License-Expression: MIT
Project-URL: Source, https://github.com/adamtheturtle/sphinx-confluencebuilder-bridge
Keywords: confluence,documentation,rst,sphinx
Classifier: Development Status :: 5 - Production/Stable
Classifier: Environment :: Web Environment
Classifier: Framework :: Pytest
Classifier: Operating System :: Microsoft :: Windows
Classifier: Operating System :: POSIX
Classifier: Programming Language :: Python :: 3 :: Only
Classifier: Programming Language :: Python :: 3.11
Classifier: Programming Language :: Python :: 3.12
Classifier: Programming Language :: Python :: 3.13
Requires-Python: >=3.11
License-File: LICENSE
Requires-Dist: beartype>=0.22.5
Requires-Dist: docutils>=0.19
Requires-Dist: sphinx>=8.2.3
Requires-Dist: sphinx-simplepdf>=1.6.0
Provides-Extra: dev
Requires-Dist: actionlint-py==1.7.8.24; extra == "dev"
Requires-Dist: beartype==0.22.5; extra == "dev"
Requires-Dist: check-manifest==0.51; extra == "dev"
Requires-Dist: deptry==0.24.0; extra == "dev"
Requires-Dist: doc8==2.0.0; extra == "dev"
Requires-Dist: doccmd==2025.11.8.1; extra == "dev"
Requires-Dist: docformatter==1.7.7; extra == "dev"
Requires-Dist: furo==2025.9.25; extra == "dev"
Requires-Dist: interrogate==1.7.0; extra == "dev"
Requires-Dist: mypy[faster-cache]==1.18.2; extra == "dev"
Requires-Dist: mypy-strict-kwargs==2025.4.3; extra == "dev"
Requires-Dist: myst-parser==4.0.1; extra == "dev"
Requires-Dist: pre-commit==4.4.0; extra == "dev"
Requires-Dist: pylint[spelling]==4.0.2; extra == "dev"
Requires-Dist: pyproject-fmt==2.11.1; extra == "dev"
Requires-Dist: pyright==1.1.407; extra == "dev"
Requires-Dist: pyroma==5.0; extra == "dev"
Requires-Dist: pytest==9.0.1; extra == "dev"
Requires-Dist: pytest-cov==7.0.0; extra == "dev"
Requires-Dist: reportlab==4.4.4; extra == "dev"
Requires-Dist: ruff==0.14.4; extra == "dev"
Requires-Dist: shellcheck-py==0.11.0.1; extra == "dev"
Requires-Dist: shfmt-py==3.12.0.2; extra == "dev"
Requires-Dist: sphinx-lint==1.0.1; extra == "dev"
Requires-Dist: sphinx-toolbox==4.0.0; extra == "dev"
Requires-Dist: sphinxcontrib-confluencebuilder==2.15.0; extra == "dev"
Requires-Dist: sphinxcontrib-spelling==8.0.1; extra == "dev"
Requires-Dist: types-docutils==0.22.2.20251006; extra == "dev"
Requires-Dist: vulture==2.14; extra == "dev"
Requires-Dist: yamlfix==1.19.0; extra == "dev"
Provides-Extra: release
Requires-Dist: check-wheel-contents==0.6.3; extra == "release"
Dynamic: license-file
